formulaic_contrasts/__init__.py
formulaic_contrasts/_contrasts.py
formulaic_contrasts/_factor_metadata.py
formulaic_contrasts/datasets.py
formulaic_contrasts-0.2.0.dist-info/METADATA
formulaic_contrasts-0.2.0.dist-info/WHEEL
formulaic_contrasts-0.2.0.dist-info/licenses/LICENSE
formulaic_contrasts-0.2.0.dist-info/RECORD
