Metadata-Version: 2.3
Name: formulaic-contrasts
Version: 0.2.0
Summary: Build contrasts for models defined with formulaic
Project-URL: Documentation, https://formulaic-contrasts.readthedocs.io/
Project-URL: Homepage, https://github.com/scverse/formulaic-contrasts
Project-URL: Source, https://github.com/scverse/formulaic-contrasts
Author: Gregor Sturm
Maintainer-email: Gregor Sturm <gregor.sturm@scverse.org>
License: BSD 3-Clause License
Classifier: Programming Language :: Python :: 3 :: Only
Classifier: Programming Language :: Python :: 3.10
Classifier: Programming Language :: Python :: 3.11
Classifier: Programming Language :: Python :: 3.12
Classifier: Programming Language :: Python :: 3.13
Requires-Python: >=3.10
Requires-Dist: formulaic
Requires-Dist: pandas
Requires-Dist: session-info
Provides-Extra: dev
Requires-Dist: pre-commit; extra == 'dev'
Requires-Dist: twine>=4.0.2; extra == 'dev'
Provides-Extra: doc
Requires-Dist: docutils!=0.18.*,!=0.19.*,>=0.8; extra == 'doc'
Requires-Dist: ipykernel; extra == 'doc'
Requires-Dist: ipython; extra == 'doc'
Requires-Dist: myst-nb>=1.1; extra == 'doc'
Requires-Dist: pandas; extra == 'doc'
Requires-Dist: setuptools; extra == 'doc'
Requires-Dist: sphinx-autodoc-typehints; extra == 'doc'
Requires-Dist: sphinx-book-theme>=1; extra == 'doc'
Requires-Dist: sphinx-copybutton; extra == 'doc'
Requires-Dist: sphinx-tabs; extra == 'doc'
Requires-Dist: sphinx>=4; extra == 'doc'
Requires-Dist: sphinxcontrib-bibtex>=1; extra == 'doc'
Requires-Dist: sphinxext-opengraph; extra == 'doc'
Requires-Dist: statsmodels; extra == 'doc'
Provides-Extra: test
Requires-Dist: coverage; extra == 'test'
Requires-Dist: numpy; extra == 'test'
Requires-Dist: pytest; extra == 'test'
